Workbook
Name CanYouRedo: 'Financial Statements'!$K$28:$M$28
Name CLASSEBITDA: 'Financial Statements'!$K$29:$M$29
Name company.name: Parms!$A$1
Name D.F.INTEREST: DebtSchedule!$K$18:$O$18
Name D.F.Interest.Expense: DebtSchedule!$K$18:$K$18
Name d.f.long.debt: DebtSchedule!$K$22:$O$22
Name D.F.LTDebt: DebtSchedule!$K$22:$K$22
Name d.f.short.debt\: DebtSchedule!$K$21:$O$21
Name D.F.STDebt: DebtSchedule!$K$21:$K$21
Name D.H.Interest.Expense: DebtSchedule!$G$18:$I$18
Name D.H.LTDebt: DebtSchedule!$G$22:$I$22
Name D.H.STDebt: DebtSchedule!$G$21:$I$21
Name dates.forecast: Parms!$J$1:$N$1
Name dates.hist: Parms!$G$1:$I$1
Name DCF.Debt: DebtSchedule!$I$9
Name DCF.Equity: 'Financial Statements'!$I$82
Name dcf.fcf.y5: 'DCF Model'!$K$24
Name DCF.Interest.Expense: DebtSchedule!$I$18
Name DCF.Pref.Stock: 'Financial Statements'!$I$78
Name DCF.Table: 'DCF Model'!$G$15:$K$24
Name dcf.terminal.ebitda: 'DCF Model'!$K$15
Name dcf.terminaldc: 'DCF Model'!$K$25
Name f.cash: 'Financial Statements'!$K$117:$O$117
Name f.cash.financing: 'Financial Statements'!$K$113:$O$113
Name f.cash.invest: 'Financial Statements'!$K$104:$O$104
Name f.cash.investment: 'Financial Statements'!$K$106:$O$106
Name F.cash.ops: 'Financial Statements'!$K$101:$O$101
Name F.COGS: 'Financial Statements'!$K$13:$O$13
Name F.delta.working.capital: 'DCF Model'!$G$21:$K$21
Name F.EBIT: 'Financial Statements'!$K$28:$O$28
Name f.equity: 'Financial Statements'!$K$82:$O$82
Name F.FIXED.COSTS: 'Financial Statements'!$K$26:$O$26
Name F.MARGIN: 'Financial Statements'!$K$15:$O$15
Name f.net.income: 'Financial Statements'!$K$37:$O$37
Name F.REV: 'Financial Statements'!$K$7:$O$7
Name goldman.fee: 'Transaction Summary'!$G$19
Name H.Amort.Exp: 'Financial Statements'!$G$25:$I$25
Name H.Capital: 'Financial Statements'!$G$84:$I$84
Name H.Cash: 'Financial Statements'!$G$117:$I$117
Name H.Cash.Financing: 'Financial Statements'!$H$113:$I$113
Name H.Cash.From.Ops: 'Financial Statements'!$H$101:$I$101
Name H.Cash.Investment: 'Financial Statements'!$H$106:$I$106
Name H.COGS: 'Financial Statements'!$G$13:$I$13
Name H.Depr.Exp: 'Financial Statements'!$G$24:$I$24
Name H.EBIT: 'Financial Statements'!$G$28:$I$28
Name H.Fixed.Costs: 'Financial Statements'!$G$26:$I$26
Name H.Gross.Margin: 'Financial Statements'!$G$15:$I$15
Name H.Net.Income: 'Financial Statements'!$G$37:$I$37
Name H.Operating.Income: 'Financial Statements'!$G$28:$I$28
Name H.Revenues: 'Financial Statements'!$G$7:$I$7
Name H.Total.Assets: 'Financial Statements'!$G$60:$I$60
Name hist.amort: 'Financial Statements'!$I$25
Name hist.cash: 'Financial Statements'!$I$46
Name hist.depreciation: 'Financial Statements'!$I$24
Name hist.EBIT: 'Financial Statements'!$I$28
Name LBO.Discount.Factors: 'LBO Returns'!$G$19:$K$19
Name LBO.equity: 'Transaction Summary'!$N$7
Name LBO.Goodwill: 'Transaction Summary'!$G$24
Name LBO.junk: 'Transaction Summary'!$N$6
Name lbo.ltdebt: DebtSchedule!$J$22

Sheet Parms
A1: Legends Inc. | G1: {=_xlfn.SEQUENCE(1,8,2022,1)} -> 2022 | H1: 2023 | I1: 2024 | J1: 2025 | K1: 2026 | L1: 2027 | M1: 2028 | N1: 2029
B2: Revenues
C3: Foot Solutions | G3: 8399 | H3: 8791 | I3: 9200 | J3: =I3*(1+J7) -> 9628.7066 | K3: =J3*(1+K7) -> 10077.035 | L3: =K3*(1+L7) -> 10546.425 | M3: =L3*(1+M7) -> 11037.582 | N3: =M3*(1+N7) -> 11551.663
C4: Greeting Fulfillments | G4: 8696 | H4: 8800 | I4: 8850 | J4: =I4*(1+J8) -> 8928.0629 | K4: =J4*(1+K8) -> 8992.8025 | L4: =K4*(1+L8) -> 9065.0683 | M4: =L4*(1+M8) -> 9134.358 | N4: =M4*(1+N8) -> 9205.9694
C5: Legendwear | G5: 8366 | H5: 8657 | I5: 8900 | J5: =I5*(1+J9) -> 9179.6977 | K5: =J5*(1+K9) -> 9452.7776 | L5: =K5*(1+L9) -> 9741.9141 | M5: =L5*(1+M9) -> 10035.807 | N5: =M5*(1+N9) -> 10340.671
B6: % Change
C7: {=+C3:C5} -> Foot Solutions | H7: =+H3/G3-1 -> 0.046672223 | I7: =+I3/H3-1 -> 0.046524855 | J7: =AVERAGE(H7:I7) -> 0.046598539 | K7: =AVERAGE(I7:J7) -> 0.046561697 | L7: =AVERAGE(J7:K7) -> 0.046580118 | M7: =AVERAGE(K7:L7) -> 0.046570907 | N7: =AVERAGE(L7:M7) -> 0.046575513
C8: Greeting Fulfillments | H8: =+H4/G4-1 -> 0.011959522 | I8: =+I4/H4-1 -> 0.0056818182 | J8: =AVERAGE(H8:I8) -> 0.0088206699 | K8: =AVERAGE(I8:J8) -> 0.007251244 | L8: =AVERAGE(J8:K8) -> 0.008035957 | M8: =AVERAGE(K8:L8) -> 0.0076436005 | N8: =AVERAGE(L8:M8) -> 0.0078397787
C9: Legendwear | H9: =+H5/G5-1 -> 0.034783648 | I9: =+I5/H5-1 -> 0.02806977 | J9: =AVERAGE(H9:I9) -> 0.031426709 | K9: =AVERAGE(I9:J9) -> 0.02974824 | L9: =AVERAGE(J9:K9) -> 0.030587474 | M9: =AVERAGE(K9:L9) -> 0.030167857 | N9: =AVERAGE(L9:M9) -> 0.030377666
B10: Cost of Goods Sold
C11: {=+C3:C5} -> Foot Solutions | G11: 0.52854836 | H11: 0.51945532 | I11: 0.52962561 | J11: =AVERAGE(G11:I11) -> 0.52587643 | K11: =AVERAGE(H11:J11) -> 0.52498579 | L11: =AVERAGE(I11:K11) -> 0.52682928 | M11: =AVERAGE(J11:L11) -> 0.52589717 | N11: =AVERAGE(K11:M11) -> 0.52590408
C12: Greeting Fulfillments | G12: 0.54951212 | H12: 0.50621255 | I12: 0.54249378 | J12: =AVERAGE(G12:I12) -> 0.53273948 | K12: =AVERAGE(H12:J12) -> 0.5271486 | L12: =AVERAGE(I12:K12) -> 0.53412729 | M12: =AVERAGE(J12:L12) -> 0.53133846 | N12: =AVERAGE(K12:M12) -> 0.53087145
C13: Legendwear | G13: 0.50169648 | H13: 0.51854696 | I13: 0.53504035 | J13: =AVERAGE(G13:I13) -> 0.51842793 | K13: =AVERAGE(H13:J13) -> 0.52400508 | L13: =AVERAGE(I13:K13) -> 0.52582446 | M13: =AVERAGE(J13:L13) -> 0.52275249 | N13: =AVERAGE(K13:M13) -> 0.52419401
B14: Operating Expenses (aka fixed costs)
C15: Rent | G15: 0.04520141 | H15: 0.041519682 | I15: 0.041485585 | J15: =AVERAGE(G15:I15) -> 0.042735559 | K15: =AVERAGE(H15:J15) -> 0.041913609 | L15: =AVERAGE(I15:K15) -> 0.042044918 | M15: =AVERAGE(J15:L15) -> 0.042231362 | N15: =AVERAGE(K15:M15) -> 0.042063296
C16: Utilities | G16: 0.039664353 | H16: 0.04825251 | I16: 0.0428629 | J16: =AVERAGE(G16:I16) -> 0.043593254 | K16: =AVERAGE(H16:J16) -> 0.044902888 | L16: =AVERAGE(I16:K16) -> 0.043786347 | M16: =AVERAGE(J16:L16) -> 0.044094163 | N16: =AVERAGE(K16:M16) -> 0.044261133
C17: Phone | G17: 0.030733282 | H17: 0.037306794 | I17: 0.041556613 | J17: =AVERAGE(G17:I17) -> 0.03653223 | K17: =AVERAGE(H17:J17) -> 0.038465212 | L17: =AVERAGE(I17:K17) -> 0.038851352 | M17: =AVERAGE(J17:L17) -> 0.037949598 | N17: =AVERAGE(K17:M17) -> 0.038422054
C18: Advertising | G18: 0.031545546 | H18: 0.037579353 | I18: 0.036485053 | J18: =AVERAGE(G18:I18) -> 0.035203317 | K18: =AVERAGE(H18:J18) -> 0.036422575 | L18: =AVERAGE(I18:K18) -> 0.036036982 | M18: =AVERAGE(J18:L18) -> 0.035887625 | N18: =AVERAGE(K18:M18) -> 0.036115727
C19: Salaries | G19: 0.037692894 | H19: 0.046375124 | I19: 0.033670329 | J19: =AVERAGE(G19:I19) -> 0.039246116 | K19: =AVERAGE(H19:J19) -> 0.039763856 | L19: =AVERAGE(I19:K19) -> 0.0375601 | M19: =AVERAGE(J19:L19) -> 0.038856691 | N19: =AVERAGE(K19:M19) -> 0.038726882
C20: Depreciation Expense | G20: 1000 | H20: =+G20 -> 1000 | I20: =+H20 -> 1000 | J20: =+I20 -> 1000 | K20: =+J20 -> 1000 | L20: =+K20 -> 1000 | M20: =+L20 -> 1000 | N20: =+M20 -> 1000
C21: Amortization Expense | G21: 250 | H21: =+G21 -> 250 | I21: =+H21 -> 250 | J21: =I21+LBO.Goodwill/20 -> 2476.6997 | K21: =+J21 -> 2476.6997 | L21: =+K21 -> 2476.6997 | M21: =+L21 -> 2476.6997 | N21: =+M21 -> 2476.6997
B22: Tax Rate | G22: 0.21
B23: Cash Dividends | G23: 1500 | H23: =+G23 -> 1500 | I23: =+H23 -> 1500 | J23: 0 | K23: =+J23 -> 0 | L23: =+K23 -> 0 | M23: =+L23 -> 0 | N23: =+M23 -> 0
B24: Stock Buybacks | G24: 500 | H24: =+G24 -> 500 | I24: =+H24 -> 500 | J24: 0 | K24: =+J24 -> 0 | L24: =+K24 -> 0 | M24: =+L24 -> 0 | N24: =+M24 -> 0
B25: Balance Sheet
C26: Working Capital
D27: Accounts Receivable (days of Sales) | G27: 60 | H27: =+G27 -> 60 | I27: =+H27 -> 60 | J27: 58 | K27: 58 | L27: 56 | M27: 56 | N27: 54
D28: Inventory (days of COGS) | G28: 32 | H28: =+G28 -> 32 | I28: =+H28 -> 32 | J28: 30 | K28: 30 | L28: 28 | M28: 28 | N28: 26
D29: Prepaid Expenses | G29: 0.03 | H29: =+G29 -> 0.03 | I29: =+H29 -> 0.03 | J29: =+I29 -> 0.03 | K29: =+J29 -> 0.03 | L29: =+K29 -> 0.03 | M29: =+L29 -> 0.03 | N29: =+M29 -> 0.03
D30: Accounts Payable (days COGS) | G30: 35 | H30: =+G30 -> 35 | I30: =+H30 -> 35 | J30: =+I30 -> 35 | K30: 37 | L30: =+K30 -> 37 | M30: 39 | N30: =+M30 -> 39
D31: Accrued Liabilities | G31: 0.03 | H31: =+G31 -> 0.03 | I31: =+H31 -> 0.03 | J31: =+I31 -> 0.03 | K31: =+J31 -> 0.03 | L31: =+K31 -> 0.03 | M31: =+L31 -> 0.03 | N31: =+M31 -> 0.03
C32: Capital Expenditure (CAPEX) | H32: 2500 | I32: =+H32 -> 2500 | J32: 1750 | K32: =J32 -> 1750 | L32: 1500 | M32: =L32 -> 1500 | N32: =+M32 -> 1500
C33: Starting Gross PP&E | G33: 6000
C34: Starting Accumulated Depreciation | G34: 1500
C35: Starting.Goodwill | G35: 2000
C36: Starting Cash | G36: 4500

Sheet Transaction Summary
A1: Transaction Summary for Leveraged Buyout
B2: Valuation | I2: Sources and Uses of Deal Cash
C3: EBITDA | G3: =SUM(hist.amort,hist.depreciation,hist.EBIT) -> 7230.6853 | J3: Sources | N3: $ | O3: % | P3: xEBITDA | Q3: Fee % | R3: Fee $
C4: Market Multiple | G4: 8 | K4: Balance Sheet Cash | N4: =hist.cash -> 3992.7969 | O4: {=N4:N7/N8} -> 0.05576666 | P4: {=N4:N8/G3} -> 0.55220173
D5: Enterprise Value | G5: =G4*G3 -> 57845.482 | K5: Revolver (Senior Debt) | N5: 18000 | O5: 0.25140269 | P5: 2.4893906 | Q5: 0.03 | R5: =Q5*LBO.Revolver -> 540
D6: Capitalization | K6: Subordinated (Junk Bonds) | N6: 18000 | O6: 0.25140269 | P6: 2.4893906 | Q6: 0.04 | R6: =Q6*LBO.junk -> 720
E7: Less: | K7: Sponsor Equity (Gecko Fund) | N7: =30000+1605.48241990259 -> 31605.482 | O7: 0.44142796 | P7: 4.3710217
F8: Debt | G8: =-DCF.Debt -> -5500 | J8: Total Sources | N8: =SUM(N4:N7) -> 71598.279 | P8: 9.9020046 | R8: =SUM(R4:R7) -> 1260
F9: Preferred Stock | G9: =-DCF.Pref.Stock -> -1500
E10: Add: | J10: Uses
F11: Cash | G11: =hist.cash -> 3992.7969 | K11: Minimum Cash Balance | N11: =min.cash -> 5000 | O11: {=N11:N16/N17} -> 0.06983408
C12: Net Offer Value to Share Holders | G12: =SUM(G5:G11) -> 54838.279 | K12: Purchase of Equity | N12: =G12 -> 54838.279 | O12: 0.76591616
D13: Offer Per Share | G13: =G12/shares.outstanding -> 46.329575 | K13: Retire Debt | N13: =-G8 -> 5500 | O13: 0.076817489
K14: Retire Preferred Shares | N14: =-G9 -> 1500 | O14: 0.020950224
B15: Other Assumptions | K15: M&A Fee | N15: =goldman.fee -> 3500 | O15: 0.048883856
C16: Revolver EBITDA Borrowing Base Multiplier | G16: 6 | K16: Debt Placement Fee | N16: =PNC.fee -> 1260 | O16: 0.017598188
C17: Revolver Availability @ Close | G17: =G16*G3 -> 43384.112 | J17: Total Uses | N17: =SUM(N11:N16) -> 71598.279
C18: Minimum Cash Balance | G18: 5000
C19: Fee: Mergers & Acquisition | G19: =3500 -> 3500 | J19: Checksum | N19: =_xlfn.LET(_xlpm.sources,N8,_xlpm.uses,N17,_xlpm.sources-_xlpm.uses) -> 0
B21: Goodwill Calculation
C22: Purchase of Equity | G22: =G12 -> 54838.279
D23: Less: Book Value of Assets | G23: =-(DCF.Equity-DCF.Pref.Stock) -> -10304.286
C24: Goodwill | G24: =SUM(G22:G23) -> 44533.993

Sheet LBO Returns
A1: LBO Returns Calculation
B2: Weighted Average Cost of Capital
C3: Capital Stack | G3: {=dates.forecast} -> 2025 | H3: 2026 | I3: 2027 | J3: 2028 | K3: 2029
D4: Revolver | G4: {=Revolver} -> 15814.109 | H4: 13445.451 | I4: 10465.326 | J4: 7149.9307 | K4: 3304.3302
D5: Subordinated Debt | G5: {=Sub.Debt} -> 18000 | H5: 18000 | I5: 18000 | J5: 18000 | K5: 18000
D6: Gecko Fund Equity | G6: {=f.equity} -> 27543.858 | H6: 28485.938 | I6: 29802.369 | J6: 31561.748 | K6: 33750.904
C7: Total Capital | G7: =SUM(G4:G6) -> 61357.967 | H7: =SUM(H4:H6) -> 59931.389 | I7: =SUM(I4:I6) -> 58267.695 | J7: =SUM(J4:J6) -> 56711.679 | K7: =SUM(K4:K6) -> 55055.234
C8: Weights
D9: {=+D4:D6} -> Revolver | G9: {=G4:K6/G7:K7} -> 0.25773522 | H9: 0.22434739 | I9: 0.17960768 | J9: 0.1260751 | K9: 0.060018457
D10: Subordinated Debt | G10: 0.29336044 | H10: 0.30034345 | I10: 0.30891904 | J10: 0.31739494 | K10: 0.32694439
D11: Gecko Fund Equity | G11: 0.44890434 | H11: 0.47530916 | I11: 0.51147328 | J11: 0.55652996 | K11: 0.61303715
C12: After-Tax Cost of Each Capital Source
D13: {=D4:D6} -> Revolver | G13: {=rate.revolver*(1-tax.rate)} -> 0.06715 | H13: 0.06715 | I13: 0.06715 | J13: 0.06715 | K13: 0.06715
D14: Subordinated Debt | G14: {=rate.sub.debt*(1-tax.rate)} -> 0.0869 | H14: 0.0869 | I14: 0.0869 | J14: 0.0869 | K14: 0.0869
D15: Gecko Fund Equity | G15: 0.2371 | H15: =G15 -> 0.2371 | I15: =H15 -> 0.2371 | J15: =I15 -> 0.2371 | K15: =J15 -> 0.2371
C16: WACC | G16: =SUMPRODUCT(G9:G11,G13:G15) -> 0.14923516 | H16: =SUMPRODUCT(H9:H11,H13:H15) -> 0.15386058 | I16: =SUMPRODUCT(I9:I11,I13:I15) -> 0.16017604 | J16: =SUMPRODUCT(J9:J11,J13:J15) -> 0.16800082 | K16: =SUMPRODUCT(K9:K11,K13:K15) -> 0.17779282
C17: Discount Factors
D18: 1-Year Factors | G18: =1/(1+G16) -> 0.87014393 | H18: =1/(1+H16) -> 0.86665583 | I18: =1/(1+I16) -> 0.86193816 | J18: =1/(1+J16) -> 0.85616379 | K18: =1/(1+K16) -> 0.84904576
D19: Cumulative Discount | G19: =PRODUCT($G18:G18) -> 0.87014393 | H19: =PRODUCT($G18:H18) -> 0.75411531 | I19: =PRODUCT($G18:I18) -> 0.65000077 | J19: =PRODUCT($G18:J18) -> 0.55650712 | K19: =PRODUCT($G18:K18) -> 0.47250001
B21: Free Cash Flow Buildup | G21: {=dates.forecast} -> 2025 | H21: 2026 | I21: 2027 | J21: 2028 | K21: 2029
C22: EBITDA | G22: {=DCF.Table} -> 7684.9185 | H22: 7792.0701 | I22: 8012.6201 | J22: 8291.5061 | K22: 8508.6504
D23: Less: Depreciation and Amort | G23: -3476.6997 | H23: -3476.6997 | I23: -3476.6997 | J23: -3476.6997 | K23: -3476.6997
C24: EBIT | G24: 4208.2188 | H24: 4315.3704 | I24: 4535.9205 | J24: 4814.8065 | K24: 5031.9507
D25: Less: Income Tax | G25: -883.72595 | H25: -906.22779 | I25: -952.5433 | J25: -1011.1094 | K25: -1056.7097
C26: EBIAT | G26: 3324.4929 | H26: 3409.1426 | I26: 3583.3772 | J26: 3803.6971 | K26: 3975.2411
D27: Add back: Depr & Amort | G27: 3476.6997 | H27: 3476.6997 | I27: 3476.6997 | J27: 3476.6997 | K27: 3476.6997
D28: Change in Working Capital | G28: 103.76086 | H28: -37.265311 | I28: 124.15693 | J28: -34.468438 | K28: 137.95622
C29: Unlevered Cash from Operations | G29: 6904.9534 | H29: 6848.577 | I29: 7184.2338 | J29: 7245.9283 | K29: 7589.897
D30: Less: CAPEX | G30: -1750 | H30: -1750 | I30: -1500 | J30: -1500 | K30: -1500
C31: Unlevered Free Cash Flow | G31: 5154.9534 | H31: 5098.577 | I31: 5684.2338 | J31: 5745.9283 | K31: 6089.897
B33: Equity Calculations | H33: Terminal Values
G34: Exit Multiplier | H34: Enterprise Value | I34: Plus: Cash | J34: Less: Debt | K34: Residual Value
G35: {=_xlfn.SEQUENCE(4,1,8,2)} -> 8 | H35: {=Term.EBITDA*_xlfn.ANCHORARRAY(G35)} -> 68069.203 | I35: =Term.Cash -> 6887.3899 | J35: =-Term.Revolver-Term.Sub.Debt -> -21304.33 | K35: {=_xlfn.BYROW(H35:J38, _xlfn.LAMBDA(_xlpm.row, SUM(_xlpm.row)))} -> 53652.263
G36: 10 | H36: 85086.504 | I36: =Term.Cash -> 6887.3899 | J36: =-Term.Revolver-Term.Sub.Debt -> -21304.33 | K36: 70669.564
G37: 12 | H37: 102103.8 | I37: =Term.Cash -> 6887.3899 | J37: =-Term.Revolver-Term.Sub.Debt -> -21304.33 | K37: 87686.865
G38: 14 | H38: 119121.11 | I38: =Term.Cash -> 6887.3899 | J38: =-Term.Revolver-Term.Sub.Debt -> -21304.33 | K38: 104704.17
B40: Gecko's Performance
C41: Gecko Fund III Initial Investment | G41: =-LBO.equity -> -31605.482 | O41: Undiscounted FCF
G42: Exit Multiplier | H42: NPV | I42: IRR | N42: Exit Multiplier | O42: {=_xlfn.SEQUENCE(1,6,0)} -> 0 | P42: 1 | Q42: 2 | R42: 3 | S42: 4 | T42: 5
G43: {=_xlfn.SEQUENCE(4,1,8,2)} -> 8 | H43: =$G$41+SUMPRODUCT(P43:T43,LBO.Discount.Factors) -> 11845.562 | I43: {=_xlfn.BYROW(O43:T46, _xlfn.LAMBDA(_xlpm.row, IRR(_xlpm.row)))} -> 0.25621931 | N43: {=_xlfn.SEQUENCE(4,1,8,2)} -> 8 | O43: =$G$41 -> -31605.482 | P43: {=_xlfn.TAKE(LBO.Unlevered.FCF,1,4)} -> 5154.9534 | Q43: 5098.577 | R43: 5684.2338 | S43: 5745.9283 | T43: {=_xlfn.TAKE(LBO.Unlevered.FCF,1,-1)+_xlfn.ANCHORARRAY(K35)} -> 59742.16
G44: 10 | H44: =$G$41+SUMPRODUCT(P44:T44,LBO.Discount.Factors) -> 19886.236 | I44: 0.30662833 | N44: 10 | O44: =$G$41 -> -31605.482 | P44: {=_xlfn.TAKE(LBO.Unlevered.FCF,1,4)} -> 5154.9534 | Q44: 5098.577 | R44: 5684.2338 | S44: 5745.9283 | T44: 76759.461
G45: 12 | H45: =$G$41+SUMPRODUCT(P45:T45,LBO.Discount.Factors) -> 27926.911 | I45: 0.34962314 | N45: 12 | O45: =$G$41 -> -31605.482 | P45: {=_xlfn.TAKE(LBO.Unlevered.FCF,1,4)} -> 5154.9534 | Q45: 5098.577 | R45: 5684.2338 | S45: 5745.9283 | T45: 93776.762
G46: 14 | H46: =$G$41+SUMPRODUCT(P46:T46,LBO.Discount.Factors) -> 35967.586 | I46: 0.38730477 | N46: 14 | O46: =$G$41 -> -31605.482 | P46: {=_xlfn.TAKE(LBO.Unlevered.FCF,1,4)} -> 5154.9534 | Q46: 5098.577 | R46: 5684.2338 | S46: 5745.9283 | T46: 110794.06

Sheet Financial Statements
A1: =company.name&" Financial Statements" -> Legends Inc. Financial Statements
B2: Income Statement | G2: {=dates.hist} -> 2022 | H2: 2023 | I2: 2024 | J2: BUYOUT | K2: {=dates.forecast} -> 2025 | L2: 2026 | M2: 2027 | N2: 2028 | O2: 2029
C3: Revenues
D4: {=+Parms!C3:C5} -> Foot Solutions | G4: {=P.H.Revenues} -> 8399 | H4: 8791 | I4: 9200 | K4: {=P.F.REV} -> 9628.7066 | L4: 10077.035 | M4: 10546.425 | N4: 11037.582 | O4: 11551.663
D5: Greeting Fulfillments | G5: 8696 | H5: 8800 | I5: 8850 | K5: 8928.0629 | L5: 8992.8025 | M5: 9065.0683 | N5: 9134.358 | O5: 9205.9694
D6: Legendwear | G6: 8366 | H6: 8657 | I6: 8900 | K6: 9179.6977 | L6: 9452.7776 | M6: 9741.9141 | N6: 10035.807 | O6: 10340.671
C7: Total Revenues | G7: =SUM(G4:G6) -> 25461 | H7: =SUM(H4:H6) -> 26248 | I7: =SUM(I4:I6) -> 26950 | K7: =SUM(K4:K6) -> 27736.467 | L7: =SUM(L4:L6) -> 28522.616 | M7: =SUM(M4:M6) -> 29353.407 | N7: =SUM(N4:N6) -> 30207.746 | O7: =SUM(O4:O6) -> 31098.303
C9: Cost of Goods Sold
D10: {=+_xlfn.ANCHORARRAY(D4)} -> Foot Solutions | G10: {=P.H.COGS*P.H.Revenues} -> 4439.2777 | H10: 4566.5317 | I10: 4872.5556 | K10: {=P.F.REV*P.F.COGS} -> 5063.5098 | L10: 5290.3004 | M10: 5556.1654 | N10: 5804.6329 | O10: 6075.0664
D11: Greeting Fulfillments | G11: 4778.5574 | H11: 4454.6704 | I11: 4801.07 | K11: 4756.3316 | L11: 4740.5433 | M11: 4841.9003 | N11: 4853.4357 | O11: 4887.1863
D12: Legendwear | G12: 4197.1927 | H12: 4489.061 | I12: 4761.8592 | K12: 4759.0117 | L12: 4953.3035 | M12: 5122.5367 | N12: 5246.243 | O12: 5420.5179
C13: Total Cost of Goods Sold | G13: =SUM(G10:G12) -> 13415.028 | H13: =SUM(H10:H12) -> 13510.263 | I13: =SUM(I10:I12) -> 14435.485 | K13: =SUM(K10:K12) -> 14578.853 | L13: =SUM(L10:L12) -> 14984.147 | M13: =SUM(M10:M12) -> 15520.602 | N13: =SUM(N10:N12) -> 15904.312 | O13: =SUM(O10:O12) -> 16382.771
C15: Gross Margin | G15: {=H.Revenues-H.COGS} -> 12045.972 | H15: 12737.737 | I15: 12514.515 | K15: {=F.REV-F.COGS} -> 13157.614 | L15: 13538.468 | M15: 13832.805 | N15: 14303.435 | O15: 14715.533
D16: % Revenues | G16: {=H.Gross.Margin/H.Revenues} -> 0.47311465 | H16: 0.48528409 | I16: 0.46436049 | K16: {=F.MARGIN/F.REV} -> 0.47437959 | L16: 0.47465732 | M16: 0.4712504 | N16: 0.47350222 | O16: 0.47319407
C18: Selling, General and Administrative Expenses
D19: Rent | G19: {=H.Revenues*P.H.Fixed.Costs} -> 1150.8731 | H19: 1089.8086 | I19: 1118.0365 | K19: {=F.REV*P.F.FIXED.COST} -> 1185.3334 | L19: 1195.4857 | M19: 1234.1616 | N19: 1275.7143 | O19: 1308.0971
D20: Utilities | G20: 1009.8941 | H20: 1266.5319 | I20: 1155.1551 | K20: 1209.1229 | L20: 1280.7478 | M20: 1285.2785 | N20: 1331.9853 | O20: 1376.4461
D21: Phone | G21: 782.5001 | H21: 979.22872 | I21: 1119.9507 | K21: 1013.275 | L21: 1097.1285 | M21: 1140.4196 | N21: 1146.3718 | O21: 1194.8607
D22: Advertising | G22: 803.18113 | H22: 986.38287 | I22: 983.27219 | K22: 976.41566 | L22: 1038.8671 | M22: 1057.8082 | N22: 1084.0843 | O22: 1123.1378
D23: Salaries | G23: 959.69878 | H23: 1217.2543 | I23: 907.41536 | K23: 1088.5486 | L23: 1134.1692 | M23: 1102.5169 | N23: 1173.7731 | O23: 1204.3403
D24: Depreciation Expense | G24: {=P.H.Depreciation.Expense} -> 1000 | H24: 1000 | I24: 1000 | K24: {=P.F.DEPREC} -> 1000 | L24: 1000 | M24: 1000 | N24: 1000 | O24: 1000
D25: Amortization Expense | G25: {=P.H.Amortization.Expense} -> 250 | H25: 250 | I25: 250 | K25: {=P.F.AMORT} -> 2476.6997 | L25: 2476.6997 | M25: 2476.6997 | N25: 2476.6997 | O25: 2476.6997
C26: Total SG&A Expenses | G26: =SUM(G19:G25) -> 5956.1472 | H26: =SUM(H19:H25) -> 6789.2064 | I26: =SUM(I19:I25) -> 6533.8299 | K26: =SUM(K19:K25) -> 8949.3952 | L26: =SUM(L19:L25) -> 9223.098 | M26: =SUM(M19:M25) -> 9296.8844 | N26: =SUM(N19:N25) -> 9488.6284 | O26: =SUM(O19:O25) -> 9683.5818
C28: Earnings Before Interest and Taxes (EBIT) | G28: {=H.Gross.Margin-H.Fixed.Costs} -> 6089.825 | H28: 5948.5305 | I28: 5980.6853 | K28: {=F.MARGIN-F.FIXED.COSTS} -> 4208.2188 | L28: 4315.3704 | M28: 4535.9205 | N28: 4814.8065 | O28: 5031.9507
D29: % Revenues | G29: {=H.Operating.Income/H.Revenues} -> 0.23918248 | H29: 0.22662795 | I29: 0.22191782 | K29: {=F.EBIT/F.REV} -> 0.15172152 | L29: 0.15129645 | M29: 0.1545279 | N29: 0.15938979 | O29: 0.16180789
C31: Interest Expense | G31: {=D.H.Interest.Expense} -> 525.5 | H31: 509.375 | I31: 370.25 | K31: {=D.F.INTEREST} -> 3324.1993 | L31: 3122.8633 | M31: 2869.5527 | N31: 2587.7441 | O31: 2260.8681
C33: Earnings Before Taxes (EBT) | G33: {=H.EBIT-G31:I31} -> 5564.325 | H33: 5439.1555 | I33: 5610.4353 | K33: =K28-K31 -> 884.01954 | L33: =L28-L31 -> 1192.5071 | M33: =M28-M31 -> 1666.3678 | N33: =N28-N31 -> 2227.0623 | O33: =O28-O31 -> 2771.0827
C35: Income Tax Expense | G35: {=+_xlfn.ANCHORARRAY(G33)*tax.rate} -> 1168.5082 | H35: 1142.2227 | I35: 1178.1914 | K35: =K33*tax.rate -> 185.6441 | L35: =L33*tax.rate -> 250.42649 | M35: =M33*tax.rate -> 349.93724 | N35: =N33*tax.rate -> 467.68309 | O35: =O33*tax.rate -> 581.92736
C37: Net Income | G37: {=+_xlfn.ANCHORARRAY(G33)-_xlfn.ANCHORARRAY(G35)} -> 4395.8167 | H37: 4296.9328 | I37: 4432.2439 | K37: =K33-K35 -> 698.37543 | L37: =L33-L35 -> 942.08059 | M37: =M33-M35 -> 1316.4306 | N37: =N33-N35 -> 1759.3793 | O37: =O33-O35 -> 2189.1553
C39: Less: Cash Dividends | G39: {=-P.H.Dividends} -> -1500 | H39: -1500 | I39: -1500 | K39: {=-P.F.DIV} -> 0 | L39: 0 | M39: 0 | N39: 0 | O39: 0
C40: Change in Retained Earnings | G40: {=+_xlfn.ANCHORARRAY(G37)+_xlfn.ANCHORARRAY(G39)} -> 2895.8167 | H40: 2796.9328 | I40: 2932.2439 | K40: =+K37+K39 -> 698.37543 | L40: =+L37+L39 -> 942.08059 | M40: =+M37+M39 -> 1316.4306 | N40: =+N37+N39 -> 1759.3793 | O40: =+O37+O39 -> 2189.1553
B43: Balance Sheet | G43: {=dates.hist} -> 2022 | H43: 2023 | I43: 2024 | J43: BUYOUT | K43: {=dates.forecast} -> 2025 | L43: 2026 | M43: 2027 | N43: 2028 | O43: 2029
C44: Assets
D45: Short Term Assets
E46: Cash | G46: {=H.Cash} -> 4500 | H46: 5168.3457 | I46: 3992.7969 | J46: =min.cash -> 5000 | K46: {=f.cash} -> 5342.9453 | L46: 5605.8019 | M46: 6042.9636 | N46: 6429.1792 | O46: 6887.3899
E47: Accounts Receivable | G47: {=H.Revenues*(P.H.Accounts.Rec.Days/365)} -> 4185.3699 | H47: 4314.7397 | I47: 4430.137 | J47: =+I47 -> 4430.137 | K47: {=F.REV*(p.f.rec.days/365)} -> 4407.4386 | L47: 4532.3608 | M47: 4503.5365 | N47: 4634.6131 | O47: 4600.8449
E48: Inventory | G48: {=H.COGS*(P.H.Inventory.Days/365)} -> 1176.112 | H48: 1184.4614 | I48: 1265.5767 | J48: =+I48 -> 1265.5767 | K48: {=F.COGS*(p.f.invent.cogs/365)} -> 1198.2619 | L48: 1231.5737 | M48: 1190.6216 | N48: 1220.0568 | O48: 1166.9919
E49: Prepaid Expenses | G49: {=P.H.Prepaids*H.Revenues} -> 763.83 | H49: 787.44 | I49: 808.5 | J49: =+I49 -> 808.5 | K49: {=p.f.prepaid*F.REV} -> 832.09402 | L49: 855.67847 | M49: 880.60222 | N49: 906.23239 | O49: 932.94909
D50: Total Short Term Assets | G50: =SUM(G46:G49) -> 10625.312 | H50: =SUM(H46:H49) -> 11454.987 | I50: =SUM(I46:I49) -> 10497.011 | J50: =SUM(J46:J49) -> 11504.214 | K50: =SUM(K46:K49) -> 11780.74 | L50: =SUM(L46:L49) -> 12225.415 | M50: =SUM(M46:M49) -> 12617.724 | N50: =SUM(N46:N49) -> 13190.082 | O50: =SUM(O46:O49) -> 13588.176
D52: Long Term Assets
E53: Gross Property, Plant & Equipment | G53: =Starting.PPE -> 6000 | H53: =+G53+Parms!H32 -> 8500 | I53: =+H53+Parms!I32 -> 11000 | J53: =I53 -> 11000 | K53: =J53+Parms!J32 -> 12750 | L53: =K53+Parms!K32 -> 14500 | M53: =L53+Parms!L32 -> 16000 | N53: =M53+Parms!M32 -> 17500 | O53: =N53+Parms!N32 -> 19000
E54: less: Accumulated Depreciation | G54: =-Starting.Acc.Dep -> -1500 | H54: =+G54-H24 -> -2500 | I54: =+H54-I24 -> -3500 | J54: =I54 -> -3500 | K54: =J54-K24 -> -4500 | L54: =K54-L24 -> -5500 | M54: =L54-M24 -> -6500 | N54: =M54-N24 -> -7500 | O54: =N54-O24 -> -8500
E55: Net PP&E | G55: =SUM(G53:G54) -> 4500 | H55: =SUM(H53:H54) -> 6000 | I55: =SUM(I53:I54) -> 7500 | J55: =I55 -> 7500 | K55: =SUM(K53:K54) -> 8250 | L55: =SUM(L53:L54) -> 9000 | M55: =SUM(M53:M54) -> 9500 | N55: =SUM(N53:N54) -> 10000 | O55: =SUM(O53:O54) -> 10500
E56: Goodwill | G56: =starting.goodwill -> 2000 | H56: =+G56-H25 -> 1750 | I56: =+H56-I25 -> 1500 | J56: =I56+LBO.Goodwill -> 46033.993 | K56: =+J56-K25 -> 43557.294 | L56: =+K56-L25 -> 41080.594 | M56: =+L56-M25 -> 38603.894 | N56: =+M56-N25 -> 36127.195 | O56: =+N56-O25 -> 33650.495
E57: Intellectual Property (IP) | G57: 1000 | H57: =+G57 -> 1000 | I57: =+H57 -> 1000 | J57: =I57 -> 1000 | K57: =+J57 -> 1000 | L57: =+K57 -> 1000 | M57: =+L57 -> 1000 | N57: =+M57 -> 1000 | O57: =+N57 -> 1000
D58: Total Long Term Assets | G58: =SUM(G55:G57) -> 7500 | H58: =SUM(H55:H57) -> 8750 | I58: =SUM(I55:I57) -> 10000 | J58: =SUM(J55:J57) -> 54533.993 | K58: =SUM(K55:K57) -> 52807.294 | L58: =SUM(L55:L57) -> 51080.594 | M58: =SUM(M55:M57) -> 49103.894 | N58: =SUM(N55:N57) -> 47127.195 | O58: =SUM(O55:O57) -> 45150.495
C60: Total Assets | G60: {=+G50:I50+G58:I58} -> 18125.312 | H60: 20204.987 | I60: 20497.011 | J60: =J58+J50 -> 66038.207 | K60: =K58+K50 -> 64588.033 | L60: =L58+L50 -> 63306.009 | M60: =M58+M50 -> 61721.618 | N60: =N58+N50 -> 60317.276 | O60: =O58+O50 -> 58738.671
C62: Capital (Liabilities and Shareholder Equity)
D63: Liabilities
E64: Short Term Liabilities
E65: Accounts Payable | G65: {=H.COGS*(P.H.Accounts.Pay.Days/365)} -> 1286.3725 | H65: 1295.5047 | I65: 1384.2246 | J65: =I65 -> 1384.2246 | K65: {=F.COGS*(p.f.payable.days/365)} -> 1397.9722 | L65: 1518.9409 | M65: 1573.3213 | N65: 1699.3648 | O65: 1750.4878
E66: Accrued Liabilities | G66: {=H.Revenues*P.H.Accrued.Liabs} -> 763.83 | H66: 787.44 | I66: 808.5 | J66: =I66 -> 808.5 | K66: {=F.REV*p.f.acru.lia} -> 832.09402 | L66: 855.67847 | M66: 880.60222 | N66: 906.23239 | O66: 932.94909
E67: Short Term Portion of LT Debt | G67: {=D.H.STDebt} -> 250 | H67: 2250 | I67: 900 | J67: =LBO.stdebt -> 2185.8906 | K67: {=d.f.short.debt\} -> 2368.6584 | L67: 2980.1254 | M67: 3315.3949 | N67: 3845.6005 | O67: 1500
E68: Total Short Term Liabilities | G68: =SUM(G65:G67) -> 2300.2025 | H68: =SUM(H65:H67) -> 4332.9447 | I68: =SUM(I65:I67) -> 3092.7246 | J68: =SUM(J65:J67) -> 4378.6152 | K68: =SUM(K65:K67) -> 4598.7246 | L68: =SUM(L65:L67) -> 5354.7448 | M68: =SUM(M65:M67) -> 5769.3184 | N68: =SUM(N65:N67) -> 6451.1977 | O68: =SUM(O65:O67) -> 4183.4369
E70: Long Term Liabilities
E71: Long Term Debt | G71: {=D.H.LTDebt} -> 7750 | H71: 5500 | I71: 4600 | J71: =lbo.ltdebt -> 33814.109 | K71: {=d.f.long.debt} -> 31445.451 | L71: 28465.326 | M71: 25149.931 | N71: 21304.33 | O71: 19804.33
E72: Capitalized Leases | G72: 1000 | H72: =+G72 -> 1000 | I72: =+H72 -> 1000 | J72: =I72 -> 1000 | K72: =+I72 -> 1000 | L72: =+K72 -> 1000 | M72: =+L72 -> 1000 | N72: =+M72 -> 1000 | O72: =+N72 -> 1000
E73: Total Long Term Liabilities | G73: =SUM(G71:G72) -> 8750 | H73: =SUM(H71:H72) -> 6500 | I73: =SUM(I71:I72) -> 5600 | J73: =SUM(J71:J72) -> 34814.109 | K73: =SUM(K71:K72) -> 32445.451 | L73: =SUM(L71:L72) -> 29465.326 | M73: =SUM(M71:M72) -> 26149.931 | N73: =SUM(N71:N72) -> 22304.33 | O73: =SUM(O71:O72) -> 20804.33
D75: Total Liabililities | G75: {=+G68:I68+G73:I73} -> 11050.203 | H75: 10832.945 | I75: 8692.7246 | J75: =J73+J68 -> 39192.725 | K75: =SUM(K73+K68) -> 37044.176 | L75: =SUM(L73+L68) -> 34820.07 | M75: =SUM(M73+M68) -> 31919.249 | N75: =SUM(N73+N68) -> 28755.528 | O75: =SUM(O73+O68) -> 24987.767
D77: Shareholder Equity
E78: Preferred Stock | G78: 1500 | H78: =+G78 -> 1500 | I78: =+H78 -> 1500 | J78: 0 | K78: =+J78 -> 0 | L78: =+K78 -> 0 | M78: =+L78 -> 0 | N78: =+M78 -> 0 | O78: =+N78 -> 0
E79: Common Stock | G79: 3500 | H79: =+G79 -> 3500 | I79: =+H79 -> 3500 | J79: =LBO.equity -> 31605.482 | K79: =J79 -> 31605.482 | L79: =+K79 -> 31605.482 | M79: =+L79 -> 31605.482 | N79: =+M79 -> 31605.482 | O79: =+N79 -> 31605.482
E80: Treasury Stock | G80: =-Parms!G24 -> -500 | H80: =+G80-Parms!H24 -> -1000 | I80: =+H80-Parms!I24 -> -1500 | J80: 0 | K80: =J80 -> 0 | L80: =+K80-Parms!K24 -> 0 | M80: =+L80-Parms!L24 -> 0 | N80: =+M80-Parms!M24 -> 0 | O80: =+N80-Parms!N24 -> 0
E81: Retained Earnings | G81: =+G40+197.436-518.143-0.0003888 -> 2575.1094 | H81: =+G81+H40 -> 5372.0422 | I81: =+H81+I40 -> 8304.2861 | J81: =-goldman.fee-PNC.fee -> -4760 | K81: =J81+K40 -> -4061.6246 | L81: =K81+L40 -> -3119.544 | M81: =L81+M40 -> -1803.1134 | N81: =M81+N40 -> -43.734168 | O81: =N81+O40 -> 2145.4211
D82: Total Shareholders Equity | G82: =SUM(G78:G81) -> 7075.1094 | H82: =SUM(H78:H81) -> 9372.0422 | I82: =SUM(I78:I81) -> 11804.286 | J82: =SUM(J78:J81) -> 26845.482 | K82: =SUM(K78:K81) -> 27543.858 | L82: =SUM(L78:L81) -> 28485.938 | M82: =SUM(M78:M81) -> 29802.369 | N82: =SUM(N78:N81) -> 31561.748 | O82: =SUM(O78:O81) -> 33750.904
D84: Total Liabilities & Equity | G84: {=+_xlfn.ANCHORARRAY(G75)+G82:I82} -> 18125.312 | H84: 20204.987 | I84: 20497.011 | J84: =J75+J82 -> 66038.207 | K84: =K82+K75 -> 64588.033 | L84: =L82+L75 -> 63306.009 | M84: =M82+M75 -> 61721.618 | N84: =N82+N75 -> 60317.276 | O84: =O82+O75 -> 58738.671
E86: Checksum | G86: {=H.Total.Assets-H.Capital} -> 4.7439244e-09 | H86: 4.7475623e-09 | I86: 4.7512003e-09 | J86: =J60-J84 -> 4.7439244e-09 | K86: =+K60-K84 -> 4.7512003e-09 | L86: =+L60-L84 -> 4.7512003e-09 | M86: =+M60-M84 -> 4.7512003e-09 | N86: =+N60-N84 -> 4.7584763e-09 | O86: =+O60-O84 -> 4.7584763e-09
B89: Statement of Changes in Cash | G89: {=dates.hist} -> 2022 | H89: 2023 | I89: 2024 | J89: BUYOUT | K89: {=dates.forecast} -> 2025 | L89: 2026 | M89: 2027 | N89: 2028 | O89: 2029
D90: Cash from Operations
E91: Net Income | G91: {=H.Net.Income} -> 4395.8167 | H91: 4296.9328 | I91: 4432.2439 | K91: {=f.net.income} -> 698.37543 | L91: 942.08059 | M91: 1316.4306 | N91: 1759.3793 | O91: 2189.1553
E92: Add Back Non Cash Items
F93: Depreciation Expense | G93: {=P.H.Depreciation.Expense} -> 1000 | H93: 1000 | I93: 1000 | K93: {=P.F.DEPREC} -> 1000 | L93: 1000 | M93: 1000 | N93: 1000 | O93: 1000
F94: Amortization Expense | G94: {=P.H.Amortization.Expense} -> 250 | H94: 250 | I94: 250 | K94: {=P.F.AMORT} -> 2476.6997 | L94: 2476.6997 | M94: 2476.6997 | N94: 2476.6997 | O94: 2476.6997
E95: Change in Working Capital
F96: {=E47:E49} -> Accounts Receivable | H96: {=+G47:G49-H47:H49} -> -129.36986 | I96: {=+H47:H49-I47:I49} -> -115.39726 | K96: =-K47+I47 -> 22.698363 | L96: {=+K47:K49-L47:L49} -> -124.9222 | M96: {=+L47:L49-M47:M49} -> 28.824347 | N96: {=+M47:M49-N47:N49} -> -131.07667 | O96: {=+N47:N49-O47:O49} -> 33.768297
F97: Inventory | H97: -8.3494009 | I97: -81.115318 | K97: =-K48+I48 -> 67.314843 | L97: -33.311836 | M97: 40.952178 | N97: -29.435217 | O97: 53.064896
F98: Prepaid Expenses | H98: -23.61 | I98: -21.06 | K98: =-K49+I49 -> -23.594016 | L98: -23.58445 | M98: -24.923756 | N98: -25.63017 | O98: -26.716703
F99: {=+E65:E66} -> Accounts Payable | H99: {=+H65:H66-G65:G66} -> 9.1321572 | I99: {=+I65:I66-H65:H66} -> 88.719879 | K99: {=+K65:K66-I65:I66} -> 13.747655 | L99: {=+L65:L66-K65:K66} -> 120.96872 | M99: {=+M65:M66-L65:L66} -> 54.380403 | N99: {=+N65:N66-M65:M66} -> 126.04345 | O99: {=+O65:O66-N65:N66} -> 51.123026
F100: Accrued Liabilities | H100: 23.61 | I100: 21.06 | K100: 23.594016 | L100: 23.58445 | M100: 24.923756 | N100: 25.63017 | O100: 26.716703
D101: Total Cash from Operations | H101: =SUM(H91:H100) -> 5418.3457 | I101: =SUM(I91:I100) -> 5574.4512 | K101: =SUM(K91:K100) -> 4278.836 | L101: =SUM(L91:L100) -> 4381.5149 | M101: =SUM(M91:M100) -> 4917.2871 | N101: =SUM(N91:N100) -> 5201.6105 | O101: =SUM(O91:O100) -> 5803.8112
D103: Cash from Investment
E104: CAPEX | G104: {=-P.H.CAPEX} -> 0 | H104: -2500 | I104: -2500 | K104: {=-p.f.capex} -> -1750 | L104: -1750 | M104: -1500 | N104: -1500 | O104: -1500
E105: Loss/Gain on Disposal of Assets | G105: 0 | H105: =+G105 -> 0 | I105: =+H105 -> 0 | K105: =+I105 -> 0 | L105: =+K105 -> 0 | M105: =+L105 -> 0 | N105: =+M105 -> 0 | O105: =+N105 -> 0
D106: Total Cash from Investment | H106: =SUM(H104:H105) -> -2500 | I106: =SUM(I104:I105) -> -2500 | K106: =SUM(K104:K105) -> -1750 | L106: =SUM(L104:L105) -> -1750 | M106: =SUM(M104:M105) -> -1500 | N106: =SUM(N104:N105) -> -1500 | O106: =SUM(O104:O105) -> -1500
D108: Cash from Financing
E109: Borrowing/(repayment) of debt | H109: =+DebtSchedule!H9-DebtSchedule!G9 -> -250 | I109: =+DebtSchedule!I9-DebtSchedule!H9 -> -2250 | K109: =+DebtSchedule!K9-DebtSchedule!J9 -> -2185.8906 | L109: =+DebtSchedule!L9-DebtSchedule!K9 -> -2368.6584 | M109: =+DebtSchedule!M9-DebtSchedule!L9 -> -2980.1254 | N109: =+DebtSchedule!N9-DebtSchedule!M9 -> -3315.3949 | O109: =+DebtSchedule!O9-DebtSchedule!N9 -> -3845.6005
E110: Issuance of Shares | H110: 0 | I110: 0 | K110: 0 | L110: 0 | M110: 0 | N110: 0 | O110: 0
E111: Cash Dividend | G111: {=-P.H.Dividends} -> -1500 | H111: -1500 | I111: -1500 | K111: {=P.F.DIV} -> 0 | L111: 0 | M111: 0 | N111: 0 | O111: 0
E112: Stock Buybacks | G112: {=-P.H.Buybacks} -> -500 | H112: -500 | I112: -500 | K112: {=-P.F.BUYBACK} -> 0 | L112: 0 | M112: 0 | N112: 0 | O112: 0
D113: Total Cash From Financing | H113: =SUM(H109:H112) -> -2250 | I113: =SUM(I109:I112) -> -4250 | K113: =SUM(K109:K112) -> -2185.8906 | L113: =SUM(L109:L112) -> -2368.6584 | M113: =SUM(M109:M112) -> -2980.1254 | N113: =SUM(N109:N112) -> -3315.3949 | O113: =SUM(O109:O112) -> -3845.6005
D115: Net Change in Cash | H115: {=H.Cash.Financing+H.Cash.From.Ops+H.Cash.Investment} -> 668.34573 | I115: -1175.5488 | K115: {=F.cash.ops+f.cash.investment+f.cash.financing} -> 342.94532 | L115: 262.85654 | M115: 437.16176 | N115: 386.21562 | O115: 458.21065
D116: Starting Cash Balance | H116: =+G117 -> 4500 | I116: =+H117 -> 5168.3457 | K116: =J117 -> 5000 | L116: =+K117 -> 5342.9453 | M116: =+L117 -> 5605.8019 | N116: =+M117 -> 6042.9636 | O116: =+N117 -> 6429.1792
D117: Ending Cash Balance | G117: =starting.cash -> 4500 | H117: =+H116+H115 -> 5168.3457 | I117: =+I116+I115 -> 3992.7969 | J117: =min.cash -> 5000 | K117: =+K116+K115 -> 5342.9453 | L117: =+L116+L115 -> 5605.8019 | M117: =+M116+M115 -> 6042.9636 | N117: =+N116+N115 -> 6429.1792 | O117: =+O116+O115 -> 6887.3899

Sheet DCF Model
A1: =+"Discount Cash Flow Model for "&company.name -> Discount Cash Flow Model for Legends Inc.
A2: General Assumptions
C3: Share Price | G3: {=_FV(H3,"Price")} -> 24.25 | H3: #VALUE!
C4: Shares Outstanding | G4: {=+_FV(H3,"Shares outstanding",TRUE)/1000000} -> 1183.656
C5: Market Capitalization | G5: {=+_FV(H3,"Market cap",TRUE)/1000000000} -> 28.703658
A7: Weighted Average Cost of Capital | G7: Amount | H7: Weight | I7: Cost
C8: Debt | G8: =DCF.Debt -> 5500 | H8: =+G8/$G$11 -> 0.31784033 | I8: =(DCF.Interest.Expense/G8)*(100%-tax.rate) -> 0.053181364
C9: Preffered Stock | G9: =+DCF.Pref.Stock -> 1500 | H9: =+G9/$G$11 -> 0.086683726 | I9: 0.0787
C10: Common Stock | G10: =+DCF.Equity-G9 -> 10304.286 | H10: =+G10/$G$11 -> 0.59547594 | I10: 0.1883
G11: =SUM(G8:G10) -> 17304.286
B12: WACC | G12: =SUMPRODUCT(H8:H10,I8:I10) -> 0.13585331
A13: Operating Forecast & Free Cash Flow Assumptions
B14: Free Cash Flow Buildup | G14: {=dates.forecast} -> 2025 | H14: 2026 | I14: 2027 | J14: 2028 | K14: 2029
C15: EBITDA | G15: {=F.EBIT+P.F.AMORT+P.F.DEPREC} -> 7684.9185 | H15: 7792.0701 | I15: 8012.6201 | J15: 8291.5061 | K15: 8508.6504
D16: Less: Depreciation and Amort | G16: {=-P.F.DEPREC-P.F.AMORT} -> -3476.6997 | H16: -3476.6997 | I16: -3476.6997 | J16: -3476.6997 | K16: -3476.6997
C17: EBIT | G17: {=F.EBIT} -> 4208.2188 | H17: 4315.3704 | I17: 4535.9205 | J17: 4814.8065 | K17: 5031.9507
D18: Less: Income Tax | G18: {=-_xlfn.ANCHORARRAY(G17)*tax.rate} -> -883.72595 | H18: -906.22779 | I18: -952.5433 | J18: -1011.1094 | K18: -1056.7097
C19: EBIAT | G19: {=+_xlfn.ANCHORARRAY(G17)+_xlfn.ANCHORARRAY(G18)} -> 3324.4929 | H19: 3409.1426 | I19: 3583.3772 | J19: 3803.6971 | K19: 3975.2411
D20: Add back: Depr & Amort | G20: {=-_xlfn.ANCHORARRAY(G16)} -> 3476.6997 | H20: 3476.6997 | I20: 3476.6997 | J20: 3476.6997 | K20: 3476.6997
D21: Change in Working Capital | G21: =+SUM('Financial Statements'!K96:K100) -> 103.76086 | H21: =+SUM('Financial Statements'!L96:L100) -> -37.265311 | I21: =+SUM('Financial Statements'!M96:M100) -> 124.15693 | J21: =+SUM('Financial Statements'!N96:N100) -> -34.468438 | K21: =+SUM('Financial Statements'!O96:O100) -> 137.95622
C22: Unlevered Cash from Operations | G22: =SUM(G19:G21) -> 6904.9534 | H22: =SUM(H19:H21) -> 6848.577 | I22: =SUM(I19:I21) -> 7184.2338 | J22: =SUM(J19:J21) -> 7245.9283 | K22: =SUM(K19:K21) -> 7589.897
D23: Less: CAPEX | G23: {=-p.f.capex} -> -1750 | H23: -1750 | I23: -1500 | J23: -1500 | K23: -1500
C24: Unlevered Free Cash Flow | G24: =SUM(G22:G23) -> 5154.9534 | H24: =SUM(H22:H23) -> 5098.577 | I24: =SUM(I22:I23) -> 5684.2338 | J24: =SUM(J22:J23) -> 5745.9283 | K24: =SUM(K22:K23) -> 6089.897
D25: Discount Factor | G25: {=1/(1+wacc)^G100} -> 0.88039537 | H25: {=1/(1+wacc)^H100} -> 0.77509601 | I25: {=1/(1+wacc)^I100} -> 0.68239094 | J25: {=1/(1+wacc)^J100} -> 0.60077383 | K25: {=1/(1+wacc)^K100} -> 0.5289185
C26: Discounted Free Cash Flow | G26: {=+G24:K24*G25:K25} -> 4538.3971 | H26: 3951.8867 | I26: 3878.8696 | J26: 3452.0034 | K26: 3221.0592
C27: Net Present Value | G27: =SUM(_xlfn.ANCHORARRAY(G26)) -> 19042.216
B29: Terminal Enterprise Valuations
C30: Perpetuity Approach
D31: Unlevered FCF Year 5 | G31: =dcf.fcf.y5 -> 6089.897
D32: Long Term Growth Rate | G32: 0.0383
D33: Forecast Year 6 FCF | G33: =G31*(1+G32) -> 6323.14
C34: Terminal Enterprise Value | G34: =+G33/(wacc-G32) -> 64817.277
C35: NPV Calculation
D36: PV of the Terminal Value | G36: =+G34*dcf.terminaldc -> 34283.057
D37: PV of the Free Cash Flows | G37: =+G27 -> 19042.216
C38: Total Enterprise Value | G38: =SUM(G36:G37) -> 53325.273
D39: Implied Terminal Value Exit Multiplier | G39: =+tv.gordon/dcf.terminal.ebitda -> 6.2671834
C41: Exit EBITDA Multiple Approach
D42: Terminal Value
E43: EBITDA Year 5 | G43: =dcf.terminal.ebitda -> 8508.6504
E44: Expected Exit Multiplier | G44: 8
D45: Terminal Value | G45: =+G44*G43 -> 68069.203
E46: PV of the Terminal Value | G46: =+G45*dcf.terminaldc -> 36003.061
E47: PV of the Free Cash Flows | G47: =G27 -> 19042.216
D48: Total Enterprise Value | G48: =SUM(G46:G47) -> 55045.277
E49: Implied Perpetual Growth Rate | G49: =(wacc-dcf.fcf.y5/G45)/(1-dcf.fcf.y5/G45) -> 0.050944902
A52: Fair Value Per Share | G52: Approach
C53: Valuation | G53: Perpetuity | H53: Multiple
D54: Enterprise Value | G54: =tv.gordon -> 53325.273 | H54: =tv.multiple -> 55045.277
D55: less: Debt | G55: =-DCF.Debt -> -5500 | H55: =-DCF.Debt -> -5500
D56: less: Pref Shares | G56: =-DCF.Pref.Stock -> -1500 | H56: =-DCF.Pref.Stock -> -1500
E57: Net Residual Value | G57: =SUM(G54:G56) -> 46325.273 | H57: =SUM(H54:H56) -> 48045.277
E58: Diluted Shares | G58: =shares.outstanding -> 1183.656 | H58: =shares.outstanding -> 1183.656
E59: Equity Value / Share | G59: =+G57/G58 -> 39.137446 | H59: =+H57/H58 -> 40.590574
B60: GF Hybrid Integrated Model
C61: Weight Based on Simulation AI Model | G61: 0.409 | H61: 0.591
D62: GFHIM Valuation | G62: =SUMPRODUCT(G59:H59,G61:H61) -> 39.996245
G64: Equity Value Per Share
I65: Long-Term Growth Rate
H66: =+G59 -> 39.137446 | I66: {=_xlfn.SEQUENCE(1,5,0.02,0.01)} -> 0.02 | J66: 0.03 | K66: 0.04 | L66: 0.05 | M66: 0.06
G67: WACC | H67: {=_xlfn.SEQUENCE(5,1,0.115,0.02)} -> 0.115 | I67: 43.101707 | J67: 47.224034 | K67: 52.445648 | L67: 59.273913 | M67: 68.585183
H68: 0.135 | I68: 34.43551 | J68: 37.00303 | K68: 40.11108 | L68: 43.950437 | M68: 48.813622
H69: 0.155 | I69: 28.345448 | J69: 30.058666 | K69: 32.069836 | L69: 34.464085 | M69: 37.362387
H70: 0.175 | I70: 23.83367 | J70: 25.034643 | K70: 26.413538 | L70: 28.013056 | M70: 29.890751
H71: 0.195 | I71: 20.358544 | J71: 21.232301 | K71: 22.218801 | L71: 23.34137 | M71: 24.630246
G73: Equity Value Per Share
I74: EBITDA Multiple
H75: =+H59 -> 40.590574 | I75: {=_xlfn.SEQUENCE(1,5,8,1)} -> 8 | J75: 9 | K75: 10 | L75: 11 | M75: 12
G76: WACC | H76: {=_xlfn.SEQUENCE(5,1,0.115,0.02)} -> 0.115 | I76: 44.416966 | J76: 48.588164 | K76: 52.759363 | L76: 56.930561 | M76: 61.101759
H77: 0.135 | I77: 40.739412 | J77: 44.55583 | K77: 48.372247 | L77: 52.188665 | M77: 56.005082
H78: 0.155 | I78: 37.411205 | J78: 40.908444 | K78: 44.405682 | L78: 47.902921 | M78: 51.400159
H79: 0.175 | I79: 34.393241 | J79: 37.602803 | K79: 40.812366 | L79: 44.021929 | M79: 47.231491
H80: 0.195 | I80: 31.651391 | J80: 34.601212 | K80: 37.551033 | L80: 40.500853 | M80: 43.450674
G82: Equity Value Per Share
G83: EBITDA % of Forecast | I83: EBITDA Multiple
H84: =H59 -> 40.590574 | I84: {=_xlfn.SEQUENCE(1,5,8,1)} -> 8 | J84: 9 | K84: 10 | L84: 11 | M84: 12
G85: {=_xlfn.SEQUENCE(5,1,70%,15%)} -> 0.7 | H85: {=_xlfn.ANCHORARRAY(G85)*dcf.terminal.ebitda} -> 5956.0553 | I85: 31.465526 | J85: 34.126998 | K85: 36.788471 | L85: 39.449943 | M85: 42.111416
G86: 0.85 | H86: 7232.3528 | I86: 36.02805 | J86: 39.259838 | K86: 42.491626 | L86: 45.723414 | M86: 48.955202
G87: 1 | H87: 8508.6504 | I87: 40.590574 | J87: 44.392678 | K87: 48.194781 | L87: 51.996885 | M87: 55.798988
G88: 1.15 | H88: 9784.948 | I88: 45.153098 | J88: 49.525517 | K88: 53.897937 | L88: 58.270356 | M88: 62.642775
G89: 1.3 | H89: 11061.246 | I89: 49.715623 | J89: 54.658357 | K89: 59.601092 | L89: 64.543826 | M89: 69.486561
B92: Football Field Calculation | G92: Low | H92: Difference | I92: High
F93: DCF Value 8X - 12X Multiplier | G93: =MIN(table.multiple) -> 31.651391 | H93: =I93-G93 -> 29.450369 | I93: =MAX(table.multiple) -> 61.101759
F94: DCF Value 2%-6% Growth Rate | G94: =MIN(table.gordon) -> 20.358544 | H94: =I94-G94 -> 48.22664 | I94: =MAX(table.gordon) -> 68.585183
F95: 52 Week Market High/Low | G95: {=_FV(H3,"52 week low",TRUE)} -> 23.6 | H95: =I95-G95 -> 9.75 | I95: {=_FV(H3,"52 week high",TRUE)} -> 33.35
F96: GFHIM Valuation | G96: =+G62 -> 39.996245 | H96: =+G96 -> 39.996245 | I96: =+H96 -> 39.996245
G100: {=_xlfn.SEQUENCE(1,5)} -> 1 | H100: 2 | I100: 3 | J100: 4 | K100: 5

Sheet DebtSchedule
A1: =company.name&" Debt Schedule" -> Legends Inc. Debt Schedule
G2: {=dates.hist} -> 2022 | H2: 2023 | I2: 2024 | J2: BUYOUT | K2: {=dates.forecast} -> 2025 | L2: 2026 | M2: 2027 | N2: 2028 | O2: 2029
B3: Debt
C4: Huntington | G4: 2000 | H4: 1750 | I4: 1500 | K4: 0 | L4: =+K4 -> 0 | M4: =+L4 -> 0 | N4: =+M4 -> 0 | O4: =+N4 -> 0 | P4: =+O4 -> 0
C5: PNC | G5: 2500 | H5: =+G5 -> 2500 | I5: =+H5 -> 2500 | K5: =0 -> 0 | L5: =0 -> 0 | M5: =0 -> 0 | N5: =0 -> 0 | O5: =0 -> 0 | P5: =0 -> 0
C6: Keybank | G6: 3500 | H6: 3500 | I6: 1500 | K6: =0 -> 0 | L6: =+K6 -> 0 | M6: =+L6 -> 0 | N6: =+M6 -> 0 | O6: =+N6 -> 0 | P6: =+O6 -> 0
C7: Revolver | G7: 0 | H7: 0 | I7: 0 | J7: =LBO.Revolver -> 18000 | K7: =J7+K26+K27 -> 15814.109 | L7: =K7+L26+L27 -> 13445.451 | M7: =L7+M26+M27 -> 10465.326 | N7: =M7+N26+N27 -> 7149.9307 | O7: =N7+O26+O27 -> 3304.3302 | P7: =O7+P26+P27 -> 1804.3302
C8: Subordinated Debt | G8: 0 | H8: 0 | I8: 0 | J8: =LBO.junk -> 18000 | K8: =LBO.junk -> 18000 | L8: =LBO.junk -> 18000 | M8: =LBO.junk -> 18000 | N8: =LBO.junk -> 18000 | O8: =LBO.junk -> 18000 | P8: =LBO.junk -> 18000
B9: Total Debt | G9: =SUM(G4:G8) -> 8000 | H9: =SUM(H4:H8) -> 7750 | I9: =SUM(I4:I8) -> 5500 | J9: =SUM(J4:J8) -> 36000 | K9: =SUM(K4:K8) -> 33814.109 | L9: =SUM(L4:L8) -> 31445.451 | M9: =SUM(M4:M8) -> 28465.326 | N9: =SUM(N4:N8) -> 25149.931 | ... P9: =SUM(P4:P8) -> 19804.33
I10: DCF.Debt
B11: Interest Rate
C12: {=+C4:C8} -> Huntington | G12: 0.0645 | H12: =+G12 -> 0.0645 | I12: =+H12 -> 0.0645 | K12: =+I12 -> 0.0645 | L12: =+K12 -> 0.0645 | M12: =+L12 -> 0.0645 | N12: =+M12 -> 0.0645 | O12: =+N12 -> 0.0645
C13: PNC | G13: 0.0725 | H13: =+G13 -> 0.0725 | I13: =+H13 -> 0.0725 | K13: =+I13 -> 0.0725 | L13: =+K13 -> 0.0725 | M13: =+L13 -> 0.0725 | N13: =+M13 -> 0.0725 | O13: =+N13 -> 0.0725
C14: Keybank | G14: 0.0615 | H14: =+G14 -> 0.0615 | I14: =+H14 -> 0.0615 | K14: =+I14 -> 0.0615 | L14: =+K14 -> 0.0615 | M14: =+L14 -> 0.0615 | N14: =+M14 -> 0.0615 | O14: =+N14 -> 0.0615
C15: Revolver | G15: 0 | H15: =+G15 -> 0 | I15: =+H15 -> 0 | K15: 0.085 | L15: =+K15 -> 0.085 | M15: =+L15 -> 0.085 | N15: =+M15 -> 0.085 | O15: =+N15 -> 0.085
C16: Subordinated Debt | G16: 0 | H16: =+G16 -> 0 | I16: =+H16 -> 0 | K16: 0.11 | L16: =+K16 -> 0.11 | M16: =+L16 -> 0.11 | N16: =+M16 -> 0.11 | O16: =+N16 -> 0.11
B18: Interest Expense | G18: =SUMPRODUCT(G4:G8,G12:G16) -> 525.5 | H18: =SUMPRODUCT(H4:H8,H12:H16) -> 509.375 | I18: =SUMPRODUCT(I4:I8,I12:I16) -> 370.25 | K18: =SUMPRODUCT(K4:K8,K12:K16) -> 3324.1993 | L18: =SUMPRODUCT(L4:L8,L12:L16) -> 3122.8633 | M18: =SUMPRODUCT(M4:M8,M12:M16) -> 2869.5527 | N18: =SUMPRODUCT(N4:N8,N12:N16) -> 2587.7441 | O18: =SUMPRODUCT(O4:O8,O12:O16) -> 2260.8681
B20: Calc Current Portion of LT Debt
C21: Current Portion | G21: =+G9-H9 -> 250 | H21: =+H9-I9 -> 2250 | I21: 900 | J21: =J9-K9 -> 2185.8906 | K21: =K9-L9 -> 2368.6584 | L21: =L9-M9 -> 2980.1254 | M21: =M9-N9 -> 3315.3949 | N21: =N9-O9 -> 3845.6005 | O21: =O9-P9 -> 1500
C22: Long Term Debt | G22: =+G9-G21 -> 7750 | H22: =+H9-H21 -> 5500 | I22: =+I9-I21 -> 4600 | J22: =+J9-J21 -> 33814.109 | K22: =+K9-K21 -> 31445.451 | L22: =+L9-L21 -> 28465.326 | M22: =+M9-M21 -> 25149.931 | N22: =+N9-N21 -> 21304.33 | O22: =+O9-O21 -> 19804.33
B24: Revolver Paydown
C25: Paydown Amounts
D26: Mandatory | K26: =-1500 -> -1500 | L26: =-1500 -> -1500 | M26: =-1500 -> -1500 | N26: =-1500 -> -1500 | O26: =-1500 -> -1500 | P26: =-1500 -> -1500
D27: Variable | K27: {=variable.paydown} -> -685.89064 | L27: -868.6584 | M27: -1480.1254 | N27: -1815.3949 | O27: -2345.6005
B29: Revolver Discretionary Paydown Calculation
C30: Levered Free Cash Flow
D31: Net Income | K31: {=f.net.income} -> 698.37543 | L31: 942.08059 | M31: 1316.4306 | N31: 1759.3793 | O31: 2189.1553
D32: Add Back
E33: Depreciation | K33: {=P.F.DEPREC} -> 1000 | L33: 1000 | M33: 1000 | N33: 1000 | O33: 1000
E34: Amortization | K34: {=P.F.AMORT} -> 2476.6997 | L34: 2476.6997 | M34: 2476.6997 | N34: 2476.6997 | O34: 2476.6997
D35: Non-Cash Interest (PIK Debt) | K35: 0 | L35: =K35 -> 0 | M35: =L35 -> 0 | N35: =M35 -> 0 | O35: =N35 -> 0
D36: Change in Working Capital | K36: {=F.delta.working.capital} -> 103.76086 | L36: -37.265311 | M36: 124.15693 | N36: -34.468438 | O36: 137.95622
D37: CAPEX | K37: {=-p.f.capex} -> -1750 | L37: -1750 | M37: -1500 | N37: -1500 | O37: -1500
C38: Net Levered Free Cash Flow | K38: =SUM(K31:K37) -> 2528.836 | L38: =SUM(L31:L37) -> 2631.5149 | M38: =SUM(M31:M37) -> 3417.2871 | N38: =SUM(N31:N37) -> 3701.6105 | O38: =SUM(O31:O37) -> 4303.8112
C40: Beginning Cash Balance | K40: {=f.cash} -> 5342.9453 | L40: 5605.8019 | M40: 6042.9636 | N40: 6429.1792 | O40: 6887.3899
D41: Less: Minimum Cash Balance | K41: =-min.cash -> -5000 | L41: =-min.cash -> -5000 | M41: =-min.cash -> -5000 | N41: =-min.cash -> -5000 | O41: =-min.cash -> -5000
D42: Plus: Levered Free Cash Flow | K42: =K38 -> 2528.836 | L42: =L38 -> 2631.5149 | M42: =M38 -> 3417.2871 | N42: =N38 -> 3701.6105 | O42: =O38 -> 4303.8112
E43: LFCF Before Scheduled Paydown | K43: =SUM(K40:K42) -> 2871.7813 | L43: =SUM(L40:L42) -> 3237.3168 | M43: =SUM(M40:M42) -> 4460.2508 | N43: =SUM(N40:N42) -> 5130.7897 | O43: =SUM(O40:O42) -> 6191.2011
F44: Less: Scheduled Paydown | K44: =K26 -> -1500 | L44: =L26 -> -1500 | M44: =M26 -> -1500 | N44: =N26 -> -1500 | O44: =O26 -> -1500
E45: LFCF After Scheduled Paydown | K45: =SUM(K43:K44) -> 1371.7813 | L45: =SUM(L43:L44) -> 1737.3168 | M45: =SUM(M43:M44) -> 2960.2508 | N45: =SUM(N43:N44) -> 3630.7897 | O45: =SUM(O43:O44) -> 4691.2011
F46: Less: Variable Paydown | I46: 0.5 | K46: {=-I46*K45:O45} -> -685.89064 | L46: -868.6584 | M46: -1480.1254 | N46: -1815.3949 | O46: -2345.6005
